powertools/__init__.py
powertools/click.py
powertools/export.py
powertools/logging.py
powertools/meta.py
powertools/pip.py
powertools/print.py
powertools/regex.py
powertools/std.py
powertools/struct.py
powertools/term.py
powertools/test.py
powertools/vendorize.py
powertools/yaml.py
powertools/setup/arguments.py
powertools-0.0.6.dist-info/METADATA
powertools-0.0.6.dist-info/RECORD
powertools-0.0.6.dist-info/WHEEL
powertools-0.0.6.dist-info/top_level.txt
powertools-0.0.6.dist-info/zip-safe
