Metadata-Version: 2.1
Name: powertools
Version: 0.0.6
Summary: 
Requires-Dist: pytest
Requires-Dist: colored-traceback
Requires-Dist: colorama
Requires-Dist: coloredlogs
Requires-Dist: termcolor
Requires-Dist: ordered-set
